README.md
setup.py
iml/__init__.py
iml/common.py
iml/datatypes.py
iml/explanations.py
iml/links.py
iml/visualizers.py
iml.egg-info/PKG-INFO
iml.egg-info/SOURCES.txt
iml.egg-info/dependency_links.txt
iml.egg-info/not-zip-safe
iml.egg-info/requires.txt
iml.egg-info/top_level.txt
iml/resources/bundle.js
iml/resources/bundle2.js
iml/resources/logoSmallGray.png