Metadata-Version: 1.0
Name: iml
Version: 0.6.1
Summary: Interpretable Machine Learning (iML) package. Explain the predictions of any model.
Home-page: http://github.com/interpretable-ml/iml
Author: Scott Lundberg
Author-email: slund1@cs.washington.edu
License: MIT
Platform: UNKNOWN
